geode_backgroundmesh/__init__.py
geode_backgroundmesh/bmesh_2d.py
geode_backgroundmesh/bmesh_3d.py
geode_backgroundmesh/geode_backgroundmesh_py_bmesh_2d.cpython-39-x86_64-linux-gnu.so
geode_backgroundmesh/geode_backgroundmesh_py_bmesh_3d.cpython-39-x86_64-linux-gnu.so
geode_backgroundmesh/geode_backgroundmesh_py_bmesh_common.cpython-39-x86_64-linux-gnu.so
geode_backgroundmesh/libGeode-BackgroundMesh_2d.so
geode_backgroundmesh/libGeode-BackgroundMesh_3d.so
geode_backgroundmesh/libGeode-BackgroundMesh_common.so
Geode_BackgroundMesh-6.0.6.dist-info/METADATA
Geode_BackgroundMesh-6.0.6.dist-info/WHEEL
Geode_BackgroundMesh-6.0.6.dist-info/top_level.txt
Geode_BackgroundMesh-6.0.6.dist-info/RECORD
