Metadata-Version: 2.1
Name: Geode-BackgroundMesh
Version: 6.0.6
Summary: Geode-solutions OpenGeode module for building background meshes
Home-page: https://github.com/Geode-solutions/Geode-BackgroundMesh
Author: Geode-solutions
Author-email: contact@geode-solutions.com
License: Proprietary
Requires-Dist: OpenGeode-core (==13.*,>=13.0.0)
Requires-Dist: Geode-Common (==24.*,>=24.0.0)
